LICENSE.txt
MANIFEST.in
README.rst
setup.py
gui_generator/__init__.py
gui_generator.egg-info/PKG-INFO
gui_generator.egg-info/SOURCES.txt
gui_generator.egg-info/dependency_links.txt
gui_generator.egg-info/top_level.txt