Metadata-Version: 2.2
Name: gui_generator
Version: 2.0.0
Summary: The GUIgenerator module facilitates the creation of simple GUI applications.
Home-page: 
Author: CPUcademy
Author-email: cpucademy@gmail.com
License: MIT
Keywords: cpucademy CPUcademy GUIgenerator guigenerator tkinter GUI gui
Classifier: Development Status :: 5 - Production/Stable
Classifier: Intended Audience :: Developers
Classifier: Operating System :: Microsoft :: Windows
Classifier: License :: OSI Approved :: MIT License
Classifier: Programming Language :: Python :: 3
License-File: LICENSE.txt
Dynamic: author
Dynamic: author-email
Dynamic: classifier
Dynamic: description
Dynamic: description-content-type
Dynamic: keywords
Dynamic: license
Dynamic: summary
